deep_apply/__init__.py
deep_apply/deep_apply.py
deep_apply/exceptions.py
deep_apply/helpers.py
deep_apply/types.py
deep_apply/utils.py
deep_apply/handlers/__init__.py
deep_apply/handlers/handle_dict.py
deep_apply/handlers/handle_list.py
deep_apply/handlers/handle_pydantic.py
deep_apply/handlers/handle_set.py
deep_apply/handlers/handle_tuple.py
deep_apply-1.0.5.dist-info/licenses/LICENSE
tests/__init__.py
tests/test_dict.py
tests/test_ignore_depth_level.py
tests/test_ignore_key.py
tests/test_ignore_key_or_depth_key.py
tests/test_list.py
tests/test_not_allow_types.py
tests/test_only_allow_types.py
tests/test_pydantic.py
tests/test_set.py
tests/test_tuple.py
deep_apply-1.0.5.dist-info/METADATA
deep_apply-1.0.5.dist-info/WHEEL
deep_apply-1.0.5.dist-info/top_level.txt
deep_apply-1.0.5.dist-info/RECORD
