Metadata-Version: 2.4
Name: deep-apply
Version: 1.0.5
Summary: Deep traverse through an object and apply a function on its values.
Home-page: https://github.com/zaironjacobs/deep-apply
Download-URL: https://github.com/zaironjacobs/deep-apply/archive/v1.0.5.tar.gz
Author: Zairon Jacobs
Author-email: zaironjacobs@gmail.com
License: MIT
Keywords: deep,traverse,apply,object,list,set,tuple,pydantic,dict
Classifier: Development Status :: 5 - Production/Stable
Classifier: Intended Audience :: Developers
Classifier: License :: OSI Approved :: MIT License
Classifier: Operating System :: OS Independent
Classifier: Programming Language :: Python :: 3.11
Classifier: Natural Language :: English
Requires-Python: >=3.11
License-File: LICENSE
Dynamic: author
Dynamic: author-email
Dynamic: classifier
Dynamic: description
Dynamic: download-url
Dynamic: home-page
Dynamic: keywords
Dynamic: license
Dynamic: license-file
Dynamic: requires-python
Dynamic: summary
